def_cache-1.0.1.dist-info/METADATA
def_cache-1.0.1.dist-info/WHEEL
def_cache-1.0.1.dist-info/entry_points.txt
def_cache-1.0.1.dist-info/licenses/LICENSE
def_cache/__init__.py
def_cache/decorator.py
def_cache/model/__init__.py
def_cache/model/models.py
def_cache/utils/__init__.py
def_cache/utils/fs.py
def_cache-1.0.1.dist-info/RECORD
